unic4py/SUT.py
unic4py/UniteAnalyser.py
unic4py/__init__.py
unic4py-0.1.4.dist-info/LICENCE
unic4py-0.1.4.dist-info/METADATA
unic4py-0.1.4.dist-info/WHEEL
unic4py-0.1.4.dist-info/top_level.txt
unic4py-0.1.4.dist-info/RECORD
